{
  "name": "Henrietta Coleman",
  "age": 61,
  "address": {
    "street": "Bagjem Pike",
    "city": "Rarhutbir",
    "state": "NE",
    "zip": "24063"
  },
  "contact": {
    "phone": "(658) 495-3187",
    "servicePhone": "800165895"
  },
  "birthday": "1963-11-13T07:09:15.617Z",
  "ip": "138.52.8.214",
  "foo": "bar",
  "profile": {
    "about": "Muj jookalo wifsios fiwaro gaurju iv pe kisa edazas ibponos jamu ru halojfok ujaku da we sonab. Jet gicdidane zi nuve kohlihud ligzuvit sakeg go lewvuemu hehogu hemtafar kujegu mi. Igibu ig do zim wa opu ducdo wejov sajef eza ib wozbetem. Awihoek fe ebrug javu hinjucged eni zet verlimsu piuri lurvunin jijafi fe goipelok fajtam lew. Zeckamzel to domun eso roji few orewankoj ga doz ezatu ruzbunej elgevo. Jufkum si kesupo ha ednaza dec pa pirictuf udsoguz ti jifuwif cugnu azo ivuhuwcu la.",
    "bio": "Vigpowa lag her or ma ibi ugiibjes saz mugvu afiiv pepalor kebuzuf wa ma hinuw kidapzi hig. Zufipa dugfalpoz ocsanti wadi kofevo turafev akemje di cusse len isuuf ka bu ju nafpim. Vaamhap obodati zebal fothibuh ododogliv vag uhead kep de nupesdep of cehtapol wogjoel."
  },
  "apiKey": "aab4cfbc1d7db59fc40e99f24869f56ba79da80aac137912cb22ed75d37d8e83",
  "currency": {
    "code": "GGP",
    "name": "Guernsey Pound"
  }
}