{
  "name": "Cora Flowers",
  "age": 54,
  "address": {
    "street": "Metim Road",
    "city": "Senikka",
    "state": "KS",
    "zip": "22721"
  },
  "contact": {
    "phone": "(319) 539-9054",
    "servicePhone": "800962228"
  },
  "birthday": "1998-03-01T05:34:01.742Z",
  "ip": "5.32.156.21",
  "foo": "bar",
  "profile": {
    "about": "Bol ebuwuvduh lutjavpad bewinoki cab gi bunpuc sesel adagor iv dastifdig gim voapi uffud varahit. Ebrot iz bobcudse ubeolucun gu gadaw lezo jupsis batvu miulzi kuda kewik ar kupfoliw fum nozefahi canpo viohusa. Viwgipaj ken cufci ocasette hovnog pe lacsanan jepgut nod varewhe hendas zomita begasa zij ged sugivaso. Kiktu ideke lu emufasif susub eriwiwa bilfus luk losjo et liazko gamib gos. Odinip po zok jabcovi zihfo des riownun lef ma bejcovje hogu lavvalfi tic mafta. Sipuor lutasu muvzo rini henosuv usiosov set oja madatufo to muwruvez fizgiibe vilav ridimud megfakev dar hazcek. Lifjafag mecpospo pitoznuc ofuadi odociw pe asatodcom ica cuvucar ulnizuc pildukle vuhir nopawju bafe uhavo rudil agucug.",
    "bio": "Irfacban boeg iteagi li oni kuk zalci oppo jifovwo bev lacehuci ta imodom beoho. Su makowhi supjo vajtu buagidug pa hovipuoc cugeawa uwowa uvizu litejzal kalgoh valew enuokiem siba. Viz mosbod cuf wuupo incobcem adev koblog pavtec ku naifi opu jubbi laksu hikhav vikkehge. Otofu uninaeh zap pe bese cagidouwe cives upekak gegpesu ola posa rek necviw kilul wig wozkor hu fehirgo."
  },
  "apiKey": "176663961d40e915c898b1af755cc04221879d80997f8b778c038573e5a794a8",
  "currency": {
    "code": "SVC",
    "name": "El Salvador Colon"
  }
}